wowicache/__init__.py
wowicache/__main__.py
wowicache/log.py
wowicache/models.py
wowicache/rescue.py
wowicache/update_cache.py
wowicache-1.0.22.dist-info/COPYING
wowicache-1.0.22.dist-info/LICENSE
wowicache-1.0.22.dist-info/METADATA
wowicache-1.0.22.dist-info/WHEEL
wowicache-1.0.22.dist-info/top_level.txt
wowicache-1.0.22.dist-info/RECORD
