Metadata-Version: 2.1
Name: wowicache
Version: 1.0.22
Summary: OPENWOWI Wowiport SQLAlchemy overlay
Home-page: https://github.com/seb-bau/wowicache
Author: Sebastian Bauhaus
Author-email: sebastian@bytewish.de
License: GPL-3.0
Classifier: Development Status :: 5 - Production/Stable
Classifier: Intended Audience :: Developers
Classifier: Intended Audience :: Other Audience
Classifier: License :: OSI Approved :: GNU General Public License v3 (GPLv3)
Classifier: Operating System :: Microsoft :: Windows
Classifier: Operating System :: POSIX :: Linux
Classifier: Programming Language :: Python :: 3
Classifier: Programming Language :: Python :: 3.4
Classifier: Programming Language :: Python :: 3.5
Classifier: Programming Language :: Python :: 3.6
Classifier: Programming Language :: Python :: 3.7
Classifier: Programming Language :: Python :: 3.8
Classifier: Programming Language :: Python :: 3.9
Classifier: Programming Language :: Python :: 3.10
Classifier: Programming Language :: Python :: 3.11
Classifier: Programming Language :: Python :: 3.12
License-File: LICENSE
License-File: COPYING
Requires-Dist: attrs >=23.1.0
Requires-Dist: cattrs >=23.1.2
Requires-Dist: certifi >=2023.7.22
Requires-Dist: charset-normalizer >=3.2.0
Requires-Dist: graypy >=2.1.0
Requires-Dist: idna >=3.4
Requires-Dist: jsonmerge >=1.9.2
Requires-Dist: jsonschema >=4.19.0
Requires-Dist: jsonschema-specifications >=2023.7.1
Requires-Dist: platformdirs >=3.10.0
Requires-Dist: pyhumps >=3.8.0
Requires-Dist: python-dotenv >=1.0.0
Requires-Dist: referencing >=0.30.2
Requires-Dist: requests >=2.31.0
Requires-Dist: requests-cache >=1.1.0
Requires-Dist: rpds-py >=0.9.2
Requires-Dist: six >=1.16.0
Requires-Dist: url-normalize >=1.4.3
Requires-Dist: urllib3 >=2.0.4
Requires-Dist: wowipy >=1.1.14
Requires-Dist: SQLAlchemy >=1.4.52
